yaturbo/__init__.py
yaturbo/apps.py
yaturbo/models.py
yaturbo/settings.py
yaturbo/toolbox.py
yaturbo/tests/conftest.py
yaturbo/tests/test_basic.py
django_yaturbo-1.0.1.dist-info/AUTHORS
django_yaturbo-1.0.1.dist-info/LICENSE
django_yaturbo-1.0.1.dist-info/METADATA
django_yaturbo-1.0.1.dist-info/WHEEL
django_yaturbo-1.0.1.dist-info/top_level.txt
django_yaturbo-1.0.1.dist-info/RECORD
